Workbook

Sheet README
B2: APPLYDESK BUSINESS TRACKER
B4: How to use this workbook
B6: 5 sheets, all linked. You only enter data in the yellow-shaded cells; everything else is calculated.
B8: 1) CLIENTS — one row per client. Enter their info, plan, start date, monthly fee, and status.
B9: 2) PAYMENTS — one row per payment received (money IN).
B10: 3) EXPENSES — one row per business expense (money OUT: tools, salaries, ads, etc.).
B11: 4) TEAM COSTS — recurring payroll for recruiters, managers, and your Workspace/Supabase bills.
B12: 5) DASHBOARD — live summary: total revenue, total costs, profit, per-client profit, cash on hand.
B14: Cell color legend
B16: • Yellow-shaded cells = you fill these in.
B17: • Blue text = input value you typed.
B18: • Black text = formula result (do not edit).
... B27: Keep this file safe. Back it up monthly to Google Drive.

Sheet Clients
A1: Client ID | B1: Full Name | C1: Email | D1: Phone | E1: Plan | F1: Monthly Fee ($) | G1: Start Date | H1: Status | I1: End Date | J1: Total Paid ($) | K1: Total Months Active | L1: Notes
A2: C001 | B2: Rahul Sharma | C2: rahul.sharma@example.com | D2: +1-555-123-4567 | E2: Job Applications | F2: 150 | G2: 46223 | H2: Active | J2: =SUMIFS(Payments!C:C, Payments!B:B, A2) -> 150 | K2: =IF(H2="Active", DATEDIF(G2, TODAY(), "m")+1, IF(ISBLANK(I2), 0, DATEDIF(G2, I2, "m")+1)) -> 1 | L2: Example row — replace or delete.
J3: =IF(A3="","",SUMIFS(Payments!C:C, Payments!B:B, A3)) | K3: =IF(A3="","",IF(H3="Active", DATEDIF(G3, TODAY(), "m")+1, IF(ISBLANK(I3), 0, DATEDIF(G3, I3, "m")+1)))
J4: =IF(A4="","",SUMIFS(Payments!C:C, Payments!B:B, A4)) | K4: =IF(A4="","",IF(H4="Active", DATEDIF(G4, TODAY(), "m")+1, IF(ISBLANK(I4), 0, DATEDIF(G4, I4, "m")+1)))
J5: =IF(A5="","",SUMIFS(Payments!C:C, Payments!B:B, A5)) | K5: =IF(A5="","",IF(H5="Active", DATEDIF(G5, TODAY(), "m")+1, IF(ISBLANK(I5), 0, DATEDIF(G5, I5, "m")+1)))
J6: =IF(A6="","",SUMIFS(Payments!C:C, Payments!B:B, A6)) | K6: =IF(A6="","",IF(H6="Active", DATEDIF(G6, TODAY(), "m")+1, IF(ISBLANK(I6), 0, DATEDIF(G6, I6, "m")+1)))
J7: =IF(A7="","",SUMIFS(Payments!C:C, Payments!B:B, A7)) | K7: =IF(A7="","",IF(H7="Active", DATEDIF(G7, TODAY(), "m")+1, IF(ISBLANK(I7), 0, DATEDIF(G7, I7, "m")+1)))
J8: =IF(A8="","",SUMIFS(Payments!C:C, Payments!B:B, A8)) | K8: =IF(A8="","",IF(H8="Active", DATEDIF(G8, TODAY(), "m")+1, IF(ISBLANK(I8), 0, DATEDIF(G8, I8, "m")+1)))
J9: =IF(A9="","",SUMIFS(Payments!C:C, Payments!B:B, A9)) | K9: =IF(A9="","",IF(H9="Active", DATEDIF(G9, TODAY(), "m")+1, IF(ISBLANK(I9), 0, DATEDIF(G9, I9, "m")+1)))
J10: =IF(A10="","",SUMIFS(Payments!C:C, Payments!B:B, A10)) | K10: =IF(A10="","",IF(H10="Active", DATEDIF(G10, TODAY(), "m")+1, IF(ISBLANK(I10), 0, DATEDIF(G10, I10, "m")+1)))
J11: =IF(A11="","",SUMIFS(Payments!C:C, Payments!B:B, A11)) | K11: =IF(A11="","",IF(H11="Active", DATEDIF(G11, TODAY(), "m")+1, IF(ISBLANK(I11), 0, DATEDIF(G11, I11, "m")+1)))
J12: =IF(A12="","",SUMIFS(Payments!C:C, Payments!B:B, A12)) | K12: =IF(A12="","",IF(H12="Active", DATEDIF(G12, TODAY(), "m")+1, IF(ISBLANK(I12), 0, DATEDIF(G12, I12, "m")+1)))
J13: =IF(A13="","",SUMIFS(Payments!C:C, Payments!B:B, A13)) | K13: =IF(A13="","",IF(H13="Active", DATEDIF(G13, TODAY(), "m")+1, IF(ISBLANK(I13), 0, DATEDIF(G13, I13, "m")+1)))
J14: =IF(A14="","",SUMIFS(Payments!C:C, Payments!B:B, A14)) | K14: =IF(A14="","",IF(H14="Active", DATEDIF(G14, TODAY(), "m")+1, IF(ISBLANK(I14), 0, DATEDIF(G14, I14, "m")+1)))
... J200: =IF(A200="","",SUMIFS(Payments!C:C, Payments!B:B, A200)) | K200: =IF(A200="","",IF(H200="Active", DATEDIF(G200, TODAY(), "m")+1, IF(ISBLANK(I200), 0, DATEDIF(G200, I200, "m")+1)))
A203: ▲ Yellow-shaded cells above are where you enter data. Formulas in cols J & K are pre-filled for 200 rows.

Sheet Payments
A1: Date | B1: Client ID | C1: Amount ($) | D1: Method | E1: For (plan/month) | F1: Notes
A2: 46223 | B2: C001 | C2: 150 | D2: Zelle | E2: Job Applications - Month 1 | F2: First payment
A503: ▲ Every incoming payment goes here. Amount auto-rolls up to Client's Total Paid and to Dashboard.

Sheet Expenses
A1: Date | B1: Category | C1: Description | D1: Amount ($) | E1: Paid To | F1: Notes
A2: 46222 | B2: Domain | C2: getapplydesk.com (1 yr) | D2: 12 | E2: Namecheap | F2: Base domain
A3: 46222 | B3: Email | C3: Google Workspace hello@ (starting Aug 2) | D3: 7 | E3: Google | F3: Monthly, billed after trial
A4: 46223 | B4: Hosting | C4: Netlify + Supabase (free tiers) | D4: 0 | E4: - | F4: $0 until scale
A5: 46223 | B5: Software | C5: Password manager (Bitwarden Family) | D5: 3.33 | E5: Bitwarden | F5: For client credential vault
A503: ▲ Categories to use consistently: Domain, Email, Hosting, Software, Ads, Team Salary, Legal, Tools, Other.

Sheet Team Costs
A1: Person | B1: Role | C1: Monthly Cost ($) | D1: Start Date | E1: Active? | F1: Notes
A2: Sahithi Velugala | B2: Recruiter | C2: 800 | D2: 46224 | E2: Yes | F2: First recruiter
A3: Google Workspace: sahithi@ | B3: Tool - per user | C3: 7 | D3: 46224 | E3: Yes | F3: Added when Sahithi joined
A53: ▲ Recurring monthly team + tool costs. Dashboard totals only rows where Active? = Yes.

Sheet Dashboard
B2: APPLYDESK LIVE DASHBOARD
B3: Updated automatically as you enter data. All figures in USD.
B5: REVENUE | E5: COSTS
B6: Total revenue (all time) | C6: =SUM(Payments!C2:C500) -> 150 | E6: Total expenses (all time) | F6: =SUM(Expenses!D2:D500) -> 22.33
B7: Payments this month | C7: =SUMPRODUCT((TEXT(Payments!A2:A500,"yyyy-mm")=TEXT(TODAY(),"yyyy-mm"))*Payments!C2:C500) -> 150 | E7: Expenses this month | F7: =SUMPRODUCT((TEXT(Expenses!A2:A500,"yyyy-mm")=TEXT(TODAY(),"yyyy-mm"))*Expenses!D2:D500) -> 22.33
B8: Payments last 30 days | C8: =SUMPRODUCT((Payments!A2:A500>=TODAY()-30)*(Payments!A2:A500<=TODAY())*Payments!C2:C500) -> 150 | E8: Recurring team costs / month | F8: =SUMIFS('Team Costs'!C2:C50,'Team Costs'!E2:E50,"Yes") -> 807
B9: Active clients | C9: =COUNTIFS(Clients!H2:H200,"Active") -> 1 | E9: Team members active | F9: =COUNTIFS('Team Costs'!E2:E50,"Yes") -> 2
B10: Total clients ever | C10: =COUNTIF(Clients!A2:A200,"?*") -> 1 | E10: Effective monthly burn | F10: =F7+F8 -> 829.33
B12: PROFITABILITY
B13: Profit this month (rev - exp) | C13: =C7-F7 -> 127.67
B14: Profit last 30 days | C14: =C8-SUMPRODUCT((Expenses!A2:A500>=TODAY()-30)*(Expenses!A2:A500<=TODAY())*Expenses!D2:D500) -> 127.67
B15: Break-even clients (@$150/mo) | C15: =IF(F10=0,0,ROUNDUP(F10/150,0)) -> 6
B17: PER CLIENT (Lifetime)
B18: Client ID | C18: Client name | D18: Months active | E18: Total paid ($) | F18: Status
B19: =IF(Clients!A3="","",Clients!A3) | C19: =IF(Clients!A3="","",Clients!B3) | D19: =IF(Clients!A3="","",Clients!K3) | E19: =IF(Clients!A3="","",Clients!J3) | F19: =IF(Clients!A3="","",Clients!H3)
B20: =IF(Clients!A4="","",Clients!A4) | C20: =IF(Clients!A4="","",Clients!B4) | D20: =IF(Clients!A4="","",Clients!K4) | E20: =IF(Clients!A4="","",Clients!J4) | F20: =IF(Clients!A4="","",Clients!H4)
B21: =IF(Clients!A5="","",Clients!A5) | C21: =IF(Clients!A5="","",Clients!B5) | D21: =IF(Clients!A5="","",Clients!K5) | E21: =IF(Clients!A5="","",Clients!J5) | F21: =IF(Clients!A5="","",Clients!H5)
B22: =IF(Clients!A6="","",Clients!A6) | C22: =IF(Clients!A6="","",Clients!B6) | D22: =IF(Clients!A6="","",Clients!K6) | E22: =IF(Clients!A6="","",Clients!J6) | F22: =IF(Clients!A6="","",Clients!H6)
B23: =IF(Clients!A7="","",Clients!A7) | C23: =IF(Clients!A7="","",Clients!B7) | D23: =IF(Clients!A7="","",Clients!K7) | E23: =IF(Clients!A7="","",Clients!J7) | F23: =IF(Clients!A7="","",Clients!H7)
B24: =IF(Clients!A8="","",Clients!A8) | C24: =IF(Clients!A8="","",Clients!B8) | D24: =IF(Clients!A8="","",Clients!K8) | E24: =IF(Clients!A8="","",Clients!J8) | F24: =IF(Clients!A8="","",Clients!H8)
B25: =IF(Clients!A9="","",Clients!A9) | C25: =IF(Clients!A9="","",Clients!B9) | D25: =IF(Clients!A9="","",Clients!K9) | E25: =IF(Clients!A9="","",Clients!J9) | F25: =IF(Clients!A9="","",Clients!H9)
B26: =IF(Clients!A10="","",Clients!A10) | C26: =IF(Clients!A10="","",Clients!B10) | D26: =IF(Clients!A10="","",Clients!K10) | E26: =IF(Clients!A10="","",Clients!J10) | F26: =IF(Clients!A10="","",Clients!H10)
B27: =IF(Clients!A11="","",Clients!A11) | C27: =IF(Clients!A11="","",Clients!B11) | D27: =IF(Clients!A11="","",Clients!K11) | E27: =IF(Clients!A11="","",Clients!J11) | F27: =IF(Clients!A11="","",Clients!H11)
B28: =IF(Clients!A12="","",Clients!A12) | C28: =IF(Clients!A12="","",Clients!B12) | D28: =IF(Clients!A12="","",Clients!K12) | E28: =IF(Clients!A12="","",Clients!J12) | F28: =IF(Clients!A12="","",Clients!H12)
B29: =IF(Clients!A13="","",Clients!A13) | C29: =IF(Clients!A13="","",Clients!B13) | D29: =IF(Clients!A13="","",Clients!K13) | E29: =IF(Clients!A13="","",Clients!J13) | F29: =IF(Clients!A13="","",Clients!H13)
B30: =IF(Clients!A14="","",Clients!A14) | C30: =IF(Clients!A14="","",Clients!B14) | D30: =IF(Clients!A14="","",Clients!K14) | E30: =IF(Clients!A14="","",Clients!J14) | F30: =IF(Clients!A14="","",Clients!H14)
... B38: =IF(Clients!A22="","",Clients!A22) | C38: =IF(Clients!A22="","",Clients!B22) | D38: =IF(Clients!A22="","",Clients!K22) | E38: =IF(Clients!A22="","",Clients!J22) | F38: =IF(Clients!A22="","",Clients!H22)
B40: ▲ Shows first 20 clients from the Clients sheet. Extend by copying row 38 down.
